dobletau_quant/__init__.py
dobletau_quant/client.py
dobletau_quant-1.0.8.dist-info/LICENSE
dobletau_quant-1.0.8.dist-info/METADATA
dobletau_quant-1.0.8.dist-info/WHEEL
dobletau_quant-1.0.8.dist-info/top_level.txt
dobletau_quant-1.0.8.dist-info/RECORD
