Metadata-Version: 2.1
Name: dobletau-quant
Version: 1.0.8
Summary: API para participar en la competencia de trading algoritmico organizada por Quant Finance Club.
Home-page: https://pypi.org/project/dobletau-quant/
Author: Percy Guerra Peña
Author-email: percy.guerra1@unmsm.edu.pe
License: MIT
Platform: UNKNOWN
Classifier: Programming Language :: Python :: 3
Classifier: License :: OSI Approved :: MIT License
Classifier: Operating System :: OS Independent
Requires-Python: >=3.7
License-File: LICENSE
Requires-Dist: requests >=2.20.0
Requires-Dist: pandas >=1.0.0
